aisci/__init__.py
aisci/main.py
aisci/secret.py
aisci-0.1.0.dist-info/entry_points.txt
aisci-0.1.0.dist-info/WHEEL
aisci-0.1.0.dist-info/METADATA
aisci-0.1.0.dist-info/RECORD
