Metadata-Version: 2.1
Name: aisci
Version: 0.1.0
Summary: 
Author: Freeman Long
Author-email: goldyard@gmail.com
Requires-Python: >=3.8,<4.0
Classifier: Programming Language :: Python :: 3
Classifier: Programming Language :: Python :: 3.8
Classifier: Programming Language :: Python :: 3.9
Classifier: Programming Language :: Python :: 3.10
Classifier: Programming Language :: Python :: 3.11
Requires-Dist: numpy (>=1.23.5,<2.0.0)
Requires-Dist: pandas (>=1.5.2,<2.0.0)
Requires-Dist: python-dotenv (>=0.19.0,<0.20.0)
Requires-Dist: toml (>=0.10.2,<0.11.0)
